kavari/__init__.py
kavari/exceptions.py
kavari/factory.py
kavari/fibonacci_retry_policy.py
kavari/kafka_client.py
kavari/kafka_consumer_manager.py
kavari/kafka_manager.py
kavari/kafka_message.py
kavari/kafka_message_consumer.py
kavari/kafka_message_deserializer.py
kavari/kafka_message_handler.py
kavari/message_type_registry.py
kavari/retry_policy.py
kavari/tooling.py
kavari-0.2.2.1.dist-info/LICENSE
kavari-0.2.2.1.dist-info/METADATA
kavari-0.2.2.1.dist-info/WHEEL
kavari-0.2.2.1.dist-info/RECORD
