Metadata-Version: 2.3
Name: kavari
Version: 0.2.2.1
Summary: Typed Python Kafka Manager - easy publish/listen to kafka topics embraced with strong types
License: Apache-2.0
Author: Szymon Dudziak
Author-email:  sdudziak@users.noreply.github.com
Requires-Python: >=3.9
Classifier: License :: OSI Approved :: Apache Software License
Requires-Dist: confluent-kafka (>=2.10.0,<3.0.0)
Requires-Dist: dacite (>=1.9.2,<2.0.0)
